semantic_version_tools/__init__.py
semantic_version_tools/version.py
semantic_version_tools-1.4.0.dist-info/METADATA
semantic_version_tools-1.4.0.dist-info/WHEEL
semantic_version_tools-1.4.0.dist-info/RECORD
