Metadata-Version: 2.3
Name: semantic-version-tools
Version: 1.4.0
Summary: Class to manage semantic versioning
Author: Romolo Politi
Author-email: romolo.politi@inaf.it
Requires-Python: >=3.10,<3.15
Classifier: Programming Language :: Python :: 3
Classifier: Programming Language :: Python :: 3.10
Classifier: Programming Language :: Python :: 3.11
Classifier: Programming Language :: Python :: 3.12
Classifier: Programming Language :: Python :: 3.13
Requires-Dist: setuptools (>=80.9.0,<81.0.0)
